lookout/__init__.py
lookout/auth.py
lookout/lookout.py
lookout/notify.py
lookout_python-1.0.5.dist-info/LICENCE.md
lookout_python-1.0.5.dist-info/METADATA
lookout_python-1.0.5.dist-info/WHEEL
lookout_python-1.0.5.dist-info/entry_points.txt
lookout_python-1.0.5.dist-info/top_level.txt
lookout_python-1.0.5.dist-info/RECORD
