Metadata-Version: 2.1
Name: lookout-python
Version: 1.0.5
Summary: Monitors your command and notifies you via Slack when you need it the most
Home-page: https://github.com/trombiano1/lookout
Author: trombiano1
Author-email: mfujitadev@gmail.com
License: MIT
Keywords: lookout notification notify
Classifier: License :: OSI Approved :: MIT License
Classifier: Programming Language :: Python :: 3.6
License-File: LICENCE.md
Requires-Dist: oauthlib
Requires-Dist: requests
